[
  {
    "title": "Forum des associations et partenaires",
    "start_time": {
      "hours": 14,
      "minutes": 0
    },
    "end_time": {
      "hours": 17,
      "minutes": 0
    },
    "professors": [],
    "groups": [
      "B1 CYBER",
      "B1 IA",
      "B2 CYBER",
      "B2 IA",
      "GRE2 FR",
      "GRE3",
      "GRE4 EN",
      "GRE4 FR",
      "ING1 EN",
      "ING1 FR",
      "ING2 EN",
      "IR2 FR",
      "IR3",
      "IR4 EN",
      "IR4 FR"
    ],
    "location": null,
    "date": 6
  },
  {
    "title": "Cours",
    "start_time": {
      "hours": 10,
      "minutes": 15
    },
    "end_time": {
      "hours": 11,
      "minutes": 45
    },
    "professors": [
      "BICCHI Erica"
    ],
    "groups": [
      "GRE3"
    ],
    "location": "E103",
    "date": 8
  },
  {
    "title": "Cours",
    "start_time": {
      "hours": 13,
      "minutes": 15
    },
    "end_time": {
      "hours": 14,
      "minutes": 45
    },
    "professors": [
      "BICCHI Erica"
    ],
    "groups": [
      "GRE3"
    ],
    "location": "E103",
    "date": 8
  },
  {
    "title": "Cours",
    "start_time": {
      "hours": 8,
      "minutes": 30
    },
    "end_time": {
      "hours": 10,
      "minutes": 0
    },
    "professors": [
      "MENET Jacqueline"
    ],
    "groups": [
      "GRE3"
    ],
    "location": "E102",
    "date": 12
  },
  {
    "title": "Cours",
    "start_time": {
      "hours": 10,
      "minutes": 15
    },
    "end_time": {
      "hours": 11,
      "minutes": 45
    },
    "professors": [
      "MENET Jacqueline"
    ],
    "groups": [
      "GRE3"
    ],
    "location": "E102",
    "date": 12
  },
  {
    "title": "Cours",
    "start_time": {
      "hours": 13,
      "minutes": 15
    },
    "end_time": {
      "hours": 14,
      "minutes": 45
    },
    "professors": [
      "HUBERT M\u00e9lody"
    ],
    "groups": [
      "GRE3"
    ],
    "location": "E102",
    "date": 12
  },
  {
    "title": "Cours",
    "start_time": {
      "hours": 15,
      "minutes": 0
    },
    "end_time": {
      "hours": 16,
      "minutes": 30
    },
    "professors": [
      "HUBERT M\u00e9lody"
    ],
    "groups": [
      "GRE3"
    ],
    "location": "E102",
    "date": 12
  },
  {
    "title": "Cours",
    "start_time": {
      "hours": 16,
      "minutes": 45
    },
    "end_time": {
      "hours": 18,
      "minutes": 15
    },
    "professors": [
      "GUILLOT Laurence"
    ],
    "groups": [
      "GRE3"
    ],
    "location": "E102",
    "date": 12
  },
  {
    "title": "Cours",
    "start_time": {
      "hours": 8,
      "minutes": 30
    },
    "end_time": {
      "hours": 10,
      "minutes": 0
    },
    "professors": [
      "BICCHI Erica"
    ],
    "groups": [
      "GRE3"
    ],
    "location": "E102",
    "date": 13
  },
  {
    "title": "Cours",
    "start_time": {
      "hours": 10,
      "minutes": 15
    },
    "end_time": {
      "hours": 11,
      "minutes": 45
    },
    "professors": [
      "ROUBERTY Fr\u00e9d\u00e9ric"
    ],
    "groups": [
      "GRE3"
    ],
    "location": "E102",
    "date": 13
  },
  {
    "title": "Pr\u00e9sentation du BDS",
    "start_time": {
      "hours": 11,
      "minutes": 45
    },
    "end_time": {
      "hours": 12,
      "minutes": 30
    },
    "professors": [],
    "groups": [
      "B1 CYBER",
      "B1 IA",
      "B2 CYBER",
      "B2 IA",
      "B3 NUM Gp Cyber",
      "B3 NUM Gp Dev",
      "BA3 NUM Gp Cyber",
      "BA3 NUM Gp Dev",
      "GRE2 FR",
      "GRE3",
      "GRE4 EN",
      "GRE4 FR",
      "ING1 EN",
      "ING1 FR",
      "ING2 EN",
      "IR2 FR",
      "IR3",
      "IR4 EN",
      "IR4 FR"
    ],
    "location": "Amphi E",
    "date": 13
  },
  {
    "title": "Cours",
    "start_time": {
      "hours": 13,
      "minutes": 15
    },
    "end_time": {
      "hours": 14,
      "minutes": 45
    },
    "professors": [
      "HUBERT M\u00e9lody"
    ],
    "groups": [
      "GRE3"
    ],
    "location": "E102",
    "date": 13
  },
  {
    "title": "Cours",
    "start_time": {
      "hours": 15,
      "minutes": 0
    },
    "end_time": {
      "hours": 16,
      "minutes": 30
    },
    "professors": [
      "HUBERT M\u00e9lody"
    ],
    "groups": [
      "GRE3"
    ],
    "location": "E102",
    "date": 13
  },
  {
    "title": "Informations",
    "start_time": {
      "hours": 16,
      "minutes": 45
    },
    "end_time": {
      "hours": 17,
      "minutes": 45
    },
    "professors": [
      "ESNAULT Amanda",
      "LUCAS Julie"
    ],
    "groups": [
      "GRE3"
    ],
    "location": "Amphi E",
    "date": 13
  },
  {
    "title": "Cours",
    "start_time": {
      "hours": 8,
      "minutes": 30
    },
    "end_time": {
      "hours": 10,
      "minutes": 0
    },
    "professors": [
      "VERON Rose-Marie"
    ],
    "groups": [
      "GRE3"
    ],
    "location": "E102",
    "date": 14
  },
  {
    "title": "Cours",
    "start_time": {
      "hours": 10,
      "minutes": 15
    },
    "end_time": {
      "hours": 11,
      "minutes": 45
    },
    "professors": [
      "VERON Rose-Marie"
    ],
    "groups": [
      "GRE3"
    ],
    "location": "E102",
    "date": 14
  },
  {
    "title": "Forum S\u00e9jours d'\u00e9tudes",
    "start_time": {
      "hours": 13,
      "minutes": 30
    },
    "end_time": {
      "hours": 15,
      "minutes": 30
    },
    "professors": [],
    "groups": [
      "Coworking C 1",
      "Coworking C 3",
      "GRE3",
      "GRE4 EN",
      "GRE4 FR",
      "IR3",
      "IR4 EN",
      "IR4 FR"
    ],
    "location": null,
    "date": 14
  },
  {
    "title": "Cours",
    "start_time": {
      "hours": 8,
      "minutes": 30
    },
    "end_time": {
      "hours": 10,
      "minutes": 0
    },
    "professors": [
      "ROUBERTY Fr\u00e9d\u00e9ric"
    ],
    "groups": [
      "GRE3"
    ],
    "location": "E102",
    "date": 15
  },
  {
    "title": "Cours",
    "start_time": {
      "hours": 10,
      "minutes": 15
    },
    "end_time": {
      "hours": 11,
      "minutes": 45
    },
    "professors": [
      "ROSSIGNOL Jean-Michel"
    ],
    "groups": [
      "GRE3"
    ],
    "location": "E102",
    "date": 15
  },
  {
    "title": "Cours",
    "start_time": {
      "hours": 13,
      "minutes": 15
    },
    "end_time": {
      "hours": 14,
      "minutes": 45
    },
    "professors": [
      "ROSSIGNOL Jean-Michel"
    ],
    "groups": [
      "GRE3"
    ],
    "location": "E102",
    "date": 15
  },
  {
    "title": "Cours",
    "start_time": {
      "hours": 15,
      "minutes": 0
    },
    "end_time": {
      "hours": 16,
      "minutes": 30
    },
    "professors": [
      "ROSSIGNOL Jean-Michel"
    ],
    "groups": [
      "GRE3"
    ],
    "location": "E102",
    "date": 15
  },
  {
    "title": "Cours",
    "start_time": {
      "hours": 16,
      "minutes": 45
    },
    "end_time": {
      "hours": 18,
      "minutes": 15
    },
    "professors": [
      "ROSSIGNOL Jean-Michel"
    ],
    "groups": [
      "GRE3"
    ],
    "location": "E102",
    "date": 15
  },
  {
    "title": "Cours",
    "start_time": {
      "hours": 8,
      "minutes": 30
    },
    "end_time": {
      "hours": 10,
      "minutes": 0
    },
    "professors": [
      "VERON Rose-Marie"
    ],
    "groups": [
      "GRE3"
    ],
    "location": "C106",
    "date": 19
  },
  {
    "title": "Cours",
    "start_time": {
      "hours": 10,
      "minutes": 15
    },
    "end_time": {
      "hours": 11,
      "minutes": 45
    },
    "professors": [
      "VERON Rose-Marie"
    ],
    "groups": [
      "GRE3"
    ],
    "location": "C106",
    "date": 19
  },
  {
    "title": "Cours",
    "start_time": {
      "hours": 13,
      "minutes": 15
    },
    "end_time": {
      "hours": 14,
      "minutes": 45
    },
    "professors": [
      "MENET Jacqueline"
    ],
    "groups": [
      "GRE3"
    ],
    "location": "C106",
    "date": 19
  },
  {
    "title": "Cours",
    "start_time": {
      "hours": 15,
      "minutes": 0
    },
    "end_time": {
      "hours": 16,
      "minutes": 30
    },
    "professors": [
      "MENET Jacqueline"
    ],
    "groups": [
      "GRE3"
    ],
    "location": "C106",
    "date": 19
  },
  {
    "title": "Cours",
    "start_time": {
      "hours": 16,
      "minutes": 45
    },
    "end_time": {
      "hours": 18,
      "minutes": 15
    },
    "professors": [],
    "groups": [
      "HAO-REN\u00a0Yan",
      "CHINOIS"
    ],
    "location": null,
    "date": 19
  },
  {
    "title": "Cours",
    "start_time": {
      "hours": 8,
      "minutes": 30
    },
    "end_time": {
      "hours": 10,
      "minutes": 0
    },
    "professors": [
      "MANCEAU Rose"
    ],
    "groups": [
      "GRE3"
    ],
    "location": "C106",
    "date": 20
  },
  {
    "title": "Cours",
    "start_time": {
      "hours": 10,
      "minutes": 15
    },
    "end_time": {
      "hours": 11,
      "minutes": 45
    },
    "professors": [
      "ROUBERTY Fr\u00e9d\u00e9ric"
    ],
    "groups": [
      "GRE3"
    ],
    "location": "C106",
    "date": 20
  },
  {
    "title": "Cours",
    "start_time": {
      "hours": 13,
      "minutes": 15
    },
    "end_time": {
      "hours": 14,
      "minutes": 45
    },
    "professors": [
      "SOLARD J\u00e9r\u00f4me"
    ],
    "groups": [
      "GRE3"
    ],
    "location": "C106",
    "date": 20
  },
  {
    "title": "Cours",
    "start_time": {
      "hours": 15,
      "minutes": 0
    },
    "end_time": {
      "hours": 16,
      "minutes": 30
    },
    "professors": [
      "SOLARD J\u00e9r\u00f4me"
    ],
    "groups": [
      "GRE3"
    ],
    "location": "C106",
    "date": 20
  },
  {
    "title": "Cours",
    "start_time": {
      "hours": 16,
      "minutes": 45
    },
    "end_time": {
      "hours": 18,
      "minutes": 15
    },
    "professors": [
      "SOLARD J\u00e9r\u00f4me"
    ],
    "groups": [
      "GRE3"
    ],
    "location": "C106",
    "date": 20
  },
  {
    "title": "Cours Gr 1",
    "start_time": {
      "hours": 8,
      "minutes": 30
    },
    "end_time": {
      "hours": 10,
      "minutes": 0
    },
    "professors": [
      "WILLIAMS Hannah"
    ],
    "groups": [
      "ING3 ANGLAIS-Gp1"
    ],
    "location": "E004",
    "date": 21
  },
  {
    "title": "Cours Gr 2",
    "start_time": {
      "hours": 8,
      "minutes": 30
    },
    "end_time": {
      "hours": 10,
      "minutes": 0
    },
    "professors": [
      "RAIMBAULT Marie"
    ],
    "groups": [
      "ING3 ANGLAIS-Gp2"
    ],
    "location": "E110",
    "date": 21
  },
  {
    "title": "Cours Gr 3",
    "start_time": {
      "hours": 8,
      "minutes": 30
    },
    "end_time": {
      "hours": 10,
      "minutes": 0
    },
    "professors": [
      "KEMP C\u00e9celia"
    ],
    "groups": [
      "ING3 ANGLAIS-Gp3"
    ],
    "location": "C210",
    "date": 21
  },
  {
    "title": "Cours Gr 4",
    "start_time": {
      "hours": 8,
      "minutes": 30
    },
    "end_time": {
      "hours": 10,
      "minutes": 0
    },
    "professors": [
      "BAINBRIDGE Julie"
    ],
    "groups": [
      "ING3 ANGLAIS-Gp4"
    ],
    "location": "C013",
    "date": 21
  },
  {
    "title": "Cours Gr 5",
    "start_time": {
      "hours": 8,
      "minutes": 30
    },
    "end_time": {
      "hours": 10,
      "minutes": 0
    },
    "professors": [
      "MCALLISTER Aileen"
    ],
    "groups": [
      "ING3 ANGLAIS-Gp5"
    ],
    "location": "C107",
    "date": 21
  },
  {
    "title": "Cours Gr 1",
    "start_time": {
      "hours": 10,
      "minutes": 15
    },
    "end_time": {
      "hours": 11,
      "minutes": 45
    },
    "professors": [
      "WILLIAMS Hannah"
    ],
    "groups": [
      "ING3 ANGLAIS-Gp1"
    ],
    "location": "E004",
    "date": 21
  },
  {
    "title": "Cours Gr 2",
    "start_time": {
      "hours": 10,
      "minutes": 15
    },
    "end_time": {
      "hours": 11,
      "minutes": 45
    },
    "professors": [
      "RAIMBAULT Marie"
    ],
    "groups": [
      "ING3 ANGLAIS-Gp2"
    ],
    "location": "E110",
    "date": 21
  },
  {
    "title": "Cours Gr 3",
    "start_time": {
      "hours": 10,
      "minutes": 15
    },
    "end_time": {
      "hours": 11,
      "minutes": 45
    },
    "professors": [
      "KEMP C\u00e9celia"
    ],
    "groups": [
      "ING3 ANGLAIS-Gp3"
    ],
    "location": "C210",
    "date": 21
  },
  {
    "title": "Cours Gr 4",
    "start_time": {
      "hours": 10,
      "minutes": 15
    },
    "end_time": {
      "hours": 11,
      "minutes": 45
    },
    "professors": [
      "BAINBRIDGE Julie"
    ],
    "groups": [
      "ING3 ANGLAIS-Gp4"
    ],
    "location": "C013",
    "date": 21
  },
  {
    "title": "Cours Gr 5",
    "start_time": {
      "hours": 10,
      "minutes": 15
    },
    "end_time": {
      "hours": 11,
      "minutes": 45
    },
    "professors": [
      "MCALLISTER Aileen"
    ],
    "groups": [
      "ING3 ANGLAIS-Gp5"
    ],
    "location": "C107",
    "date": 21
  },
  {
    "title": "Cours",
    "start_time": {
      "hours": 8,
      "minutes": 30
    },
    "end_time": {
      "hours": 10,
      "minutes": 0
    },
    "professors": [
      "HUBERT M\u00e9lody"
    ],
    "groups": [
      "GRE3"
    ],
    "location": "C106",
    "date": 22
  },
  {
    "title": "Cours",
    "start_time": {
      "hours": 10,
      "minutes": 15
    },
    "end_time": {
      "hours": 11,
      "minutes": 45
    },
    "professors": [
      "BICCHI Erica"
    ],
    "groups": [
      "GRE3"
    ],
    "location": "C106",
    "date": 22
  },
  {
    "title": "Cours",
    "start_time": {
      "hours": 13,
      "minutes": 15
    },
    "end_time": {
      "hours": 14,
      "minutes": 45
    },
    "professors": [
      "RIMAUD Anne-Charlotte"
    ],
    "groups": [
      "GRE3"
    ],
    "location": "C106",
    "date": 22
  },
  {
    "title": "Cours",
    "start_time": {
      "hours": 15,
      "minutes": 0
    },
    "end_time": {
      "hours": 16,
      "minutes": 30
    },
    "professors": [
      "RIMAUD Anne-Charlotte"
    ],
    "groups": [
      "GRE3"
    ],
    "location": "C109",
    "date": 22
  },
  {
    "title": "Cours",
    "start_time": {
      "hours": 8,
      "minutes": 30
    },
    "end_time": {
      "hours": 10,
      "minutes": 0
    },
    "professors": [
      "CABALLERO FERN\u00c1NDEZ Elena",
      "CORDOVILLA Teresa",
      "CORONADO ROQUE Pureza",
      "MEJIA RENDON Alvaro",
      "THARRAULT M\u00e9lanie"
    ],
    "groups": [
      "ING3 ESP"
    ],
    "location": "Amphi A",
    "date": 26
  },
  {
    "title": "Cours",
    "start_time": {
      "hours": 8,
      "minutes": 30
    },
    "end_time": {
      "hours": 10,
      "minutes": 0
    },
    "professors": [
      "BALUTSCH Sascha",
      "DOBROSCHKE Stephan"
    ],
    "groups": [
      "ING3 ALL"
    ],
    "location": "E102",
    "date": 26
  },
  {
    "title": "Examen",
    "start_time": {
      "hours": 10,
      "minutes": 15
    },
    "end_time": {
      "hours": 11,
      "minutes": 45
    },
    "professors": [
      "BACHELET Martine",
      "JEUNEHOMME Bernadette"
    ],
    "groups": [
      "GRE3"
    ],
    "location": "Amphi A",
    "date": 26
  },
  {
    "title": "Cours",
    "start_time": {
      "hours": 13,
      "minutes": 15
    },
    "end_time": {
      "hours": 14,
      "minutes": 45
    },
    "professors": [
      "FUENTES Jos\u00e9"
    ],
    "groups": [
      "GRE3"
    ],
    "location": "C106",
    "date": 26
  },
  {
    "title": "Cours",
    "start_time": {
      "hours": 15,
      "minutes": 0
    },
    "end_time": {
      "hours": 16,
      "minutes": 30
    },
    "professors": [
      "FUENTES Jos\u00e9"
    ],
    "groups": [
      "GRE3"
    ],
    "location": "C106",
    "date": 26
  },
  {
    "title": "Cours",
    "start_time": {
      "hours": 16,
      "minutes": 45
    },
    "end_time": {
      "hours": 18,
      "minutes": 15
    },
    "professors": [
      "FUENTES Jos\u00e9"
    ],
    "groups": [
      "GRE3"
    ],
    "location": "C106",
    "date": 26
  },
  {
    "title": "Cours",
    "start_time": {
      "hours": 8,
      "minutes": 30
    },
    "end_time": {
      "hours": 10,
      "minutes": 0
    },
    "professors": [
      "MENET Jacqueline"
    ],
    "groups": [
      "GRE3"
    ],
    "location": "C104",
    "date": 27
  },
  {
    "title": "Cours",
    "start_time": {
      "hours": 10,
      "minutes": 15
    },
    "end_time": {
      "hours": 11,
      "minutes": 45
    },
    "professors": [
      "MENET Jacqueline"
    ],
    "groups": [
      "GRE3"
    ],
    "location": "C104",
    "date": 27
  },
  {
    "title": "Cours",
    "start_time": {
      "hours": 13,
      "minutes": 15
    },
    "end_time": {
      "hours": 14,
      "minutes": 45
    },
    "professors": [
      "MANCEAU Rose"
    ],
    "groups": [
      "GRE3"
    ],
    "location": "E102",
    "date": 27
  },
  {
    "title": "Cours",
    "start_time": {
      "hours": 15,
      "minutes": 0
    },
    "end_time": {
      "hours": 16,
      "minutes": 30
    },
    "professors": [
      "MANCEAU Rose"
    ],
    "groups": [
      "GRE3"
    ],
    "location": "E102",
    "date": 27
  },
  {
    "title": "Cours Gr 1",
    "start_time": {
      "hours": 8,
      "minutes": 30
    },
    "end_time": {
      "hours": 10,
      "minutes": 0
    },
    "professors": [
      "WILLIAMS Hannah"
    ],
    "groups": [
      "ING3 ANGLAIS-Gp1"
    ],
    "location": "E004",
    "date": 28
  },
  {
    "title": "Cours Gr 2",
    "start_time": {
      "hours": 8,
      "minutes": 30
    },
    "end_time": {
      "hours": 10,
      "minutes": 0
    },
    "professors": [
      "RAIMBAULT Marie"
    ],
    "groups": [
      "ING3 ANGLAIS-Gp2"
    ],
    "location": "C209",
    "date": 28
  },
  {
    "title": "Cours Gr 3",
    "start_time": {
      "hours": 8,
      "minutes": 30
    },
    "end_time": {
      "hours": 10,
      "minutes": 0
    },
    "professors": [
      "KEMP C\u00e9celia"
    ],
    "groups": [
      "ING3 ANGLAIS-Gp3"
    ],
    "location": "C210",
    "date": 28
  },
  {
    "title": "Cours Gr 4",
    "start_time": {
      "hours": 8,
      "minutes": 30
    },
    "end_time": {
      "hours": 10,
      "minutes": 0
    },
    "professors": [
      "BAINBRIDGE Julie"
    ],
    "groups": [
      "ING3 ANGLAIS-Gp4"
    ],
    "location": "C013",
    "date": 28
  },
  {
    "title": "Cours Gr 5",
    "start_time": {
      "hours": 8,
      "minutes": 30
    },
    "end_time": {
      "hours": 10,
      "minutes": 0
    },
    "professors": [
      "MCALLISTER Aileen"
    ],
    "groups": [
      "ING3 ANGLAIS-Gp5"
    ],
    "location": "C201",
    "date": 28
  },
  {
    "title": "Cours Gr 1",
    "start_time": {
      "hours": 10,
      "minutes": 15
    },
    "end_time": {
      "hours": 11,
      "minutes": 45
    },
    "professors": [
      "WILLIAMS Hannah"
    ],
    "groups": [
      "ING3 ANGLAIS-Gp1"
    ],
    "location": "E004",
    "date": 28
  },
  {
    "title": "Cours Gr 2",
    "start_time": {
      "hours": 10,
      "minutes": 15
    },
    "end_time": {
      "hours": 11,
      "minutes": 45
    },
    "professors": [
      "RAIMBAULT Marie"
    ],
    "groups": [
      "ING3 ANGLAIS-Gp2"
    ],
    "location": "C209",
    "date": 28
  },
  {
    "title": "Cours Gr 3",
    "start_time": {
      "hours": 10,
      "minutes": 15
    },
    "end_time": {
      "hours": 11,
      "minutes": 45
    },
    "professors": [
      "KEMP C\u00e9celia"
    ],
    "groups": [
      "ING3 ANGLAIS-Gp3"
    ],
    "location": "C210",
    "date": 28
  },
  {
    "title": "Cours Gr 4",
    "start_time": {
      "hours": 10,
      "minutes": 15
    },
    "end_time": {
      "hours": 11,
      "minutes": 45
    },
    "professors": [
      "BAINBRIDGE Julie"
    ],
    "groups": [
      "ING3 ANGLAIS-Gp4"
    ],
    "location": "C013",
    "date": 28
  },
  {
    "title": "Cours Gr 5",
    "start_time": {
      "hours": 10,
      "minutes": 15
    },
    "end_time": {
      "hours": 11,
      "minutes": 45
    },
    "professors": [
      "MCALLISTER Aileen"
    ],
    "groups": [
      "ING3 ANGLAIS-Gp5"
    ],
    "location": "C201",
    "date": 28
  },
  {
    "title": "WEI",
    "start_time": {
      "hours": 8,
      "minutes": 30
    },
    "end_time": {
      "hours": 16,
      "minutes": 30
    },
    "professors": [],
    "groups": [
      "B1 CYBER",
      "B1 IA",
      "B1 METI",
      "B2 CYBER",
      "B2 IA",
      "B3 CYBER",
      "B3 NUM Gp Cyber",
      "B3 NUM Gp Dev",
      "GRE2 FR",
      "GRE3",
      "GRE4 EN",
      "GRE4 FR",
      "ING1 EN",
      "ING1 FR",
      "ING2 EN",
      "IR2 FR",
      "IR3",
      "IR4 EN",
      "IR4 FR"
    ],
    "location": null,
    "date": 29
  }
]